tvpulse/__init__.py
tvpulse/api.py
tvpulse/client.py
tvpulse/exceptions.py
tvpulse/models.py
tvpulse-0.1.2.dist-info/licenses/LICENSE
tvpulse-0.1.2.dist-info/METADATA
tvpulse-0.1.2.dist-info/WHEEL
tvpulse-0.1.2.dist-info/top_level.txt
tvpulse-0.1.2.dist-info/RECORD
