Metadata-Version: 2.4
Name: tvpulse
Version: 0.1.2
Summary: Official TVPulse SDK for Python
Author-email: SDIO <dev@sdio.io>
Project-URL: Homepage, https://github.com/sdio/tvpulse-python-sdk
Project-URL: Bug Tracker, https://github.com/sdio/tvpulse-python-sdk/issues
Classifier: Programming Language :: Python :: 3
Classifier: License :: OSI Approved :: MIT License
Classifier: Operating System :: OS Independent
Requires-Python: >=3.7
License-File: LICENSE
Requires-Dist: requests
Requires-Dist: pydantic
Dynamic: license-file
